{
  "id": "shoola",
  "name": "சூல",
  "englishName": "Shoola",
  "effect": "கூர்மை",
  "rulingPlanet": "Mars",
  "element": "Fire",
  "quality": "Rajasic",
  "bestTime": "தவிர்க்கவும் (Avoid)",
  "description": "சூல யோகம் கூர்மையான மற்றும் தீவிரமான செயல்களுக்கு ஏற்ற யோகம். இது பாதகமான யோகமாக கருதப்பட்டாலும், சரியான பயன்பாட்டில் சக்திவாய்ந்த பலன்களைத் தரும்.",
  "keyBenefits": [
    "கூர்மையான அறிவு",
    "தீவிர முயற்சிகளில் வெற்றி",
    "பகைவர்களை வெல்லுதல்",
    "கடுமையான சவால்களை எதிர்கொள்ளுதல்",
    "தீர்க்கமான செயல்கள்"
  ],
  "remedies": [
    "சிவ பூஜை செய்வது",
    "ருத்ர மந்திரம் ஜபிப்பது",
    "செவ்வாய் வழிபாடு",
    "சிவப்பு மலர்கள் அர்ப்பணம்",
    "அஞ்சனேய வழிபாடு"
  ],
  "activities": {
    "favorable": [
      "பகைவர்களை வெல்லுதல்",
      "கடினமான பணிகள்",
      "சட்ட நடவடிக்கைகள்",
      "போராட்டம் மற்றும் போட்டி",
      "பாதुகாப்பு நடவடிக்கைகள்"
    ],
    "unfavorable": [
      "திருமண நிச்சயம்",
      "புதிய நட்பு",
      "அமைதியான செயல்கள்",
      "கல்வி தொடங்குதல்",
      "புண்ணிய காரியங்கள்"
    ]
  },
  "compatibility": {
    "zodiacSigns": ["Aries", "Scorpio", "Leo"],
    "nakshatras": ["Ashwini", "Magha", "Jyeshtha"],
    "planets": ["Mars", "Sun", "Ketu"]
  },
  "mythology": "சூல யோகம் சிவ பெருமானின் திரிசூலத்தைக் குறிக்கிறது. இது தீய சக்திகளை அழித்து, நீதியை நிலைநாட்டும் சக்தி வாய்ந்த ஆயுதம் போன்ற யோகம்.",
  "duration": "13 hours 20 minutes",
  "frequency": "Every 15 days approximately"
}
